LICENSE
MANIFEST.in
README.md
requirements.txt
setup.py
librec.egg-info/PKG-INFO
librec.egg-info/SOURCES.txt
librec.egg-info/dependency_links.txt
librec.egg-info/requires.txt
librec.egg-info/top_level.txt
libreco/__init__.py
libreco/algorithms/Als.py
libreco/algorithms/Als_cy.c
libreco/algorithms/Als_cy.pyx
libreco/algorithms/Als_rating_cy.c
libreco/algorithms/Als_rating_cy.pyx
libreco/algorithms/BPR.py
libreco/algorithms/Base.py
libreco/algorithms/DeepFM.py
libreco/algorithms/FM.py
libreco/algorithms/NCF.py
libreco/algorithms/SVD.py
libreco/algorithms/SVDpp.py
libreco/algorithms/__init__.py
libreco/algorithms/item_KNN.py
libreco/algorithms/setup.py
libreco/algorithms/superSVD.py
libreco/algorithms/superSVD_cy.c
libreco/algorithms/superSVD_cy.pyx
libreco/algorithms/superSVD_cys.c
libreco/algorithms/superSVD_cys.pyx
libreco/algorithms/user_KNN.py
libreco/algorithms/wide_deep.py
libreco/dataset/DatasetFeat.py
libreco/dataset/DatasetPure.py
libreco/dataset/Dataset_orig.py
libreco/dataset/__init__.py
libreco/dataset/preprocessing.py
libreco/evaluate/__init__.py
libreco/evaluate/evaluate.py
libreco/utils/__init__.py
libreco/utils/baseline_estimates.py
libreco/utils/initializers.py
libreco/utils/intersect.py
libreco/utils/sampling.py
libreco/utils/serialization.py
libreco/utils/setup.py
libreco/utils/similarities.py
libreco/utils/similarities_cy.c
libreco/utils/similarities_cy.pyx
serving/deploy_feat_flask.py
serving/deploy_feat_request.py
serving/deploy_pure_flask.py
serving/deploy_pure_request.py
serving/tf_serving.py
serving/tf_shell.sh