Metadata-Version: 2.1
Name: librec
Version: 0.0.2
Summary: A collaborative-filtering and content-based recommender system for both explicit and implicit datasets.
Home-page: https://github.com/massquantity/LibRecommender
Author: massquantity
Author-email: wdmjjxg@163.com
License: MIT
Keywords: Matrix Factorization,Collaborative Filtering,Content-Based,Recommender System,Deep Learning,Data Mining
Platform: UNKNOWN
Classifier: Development Status :: 3 - Alpha
Classifier: Intended Audience :: Developers
Classifier: Intended Audience :: Education
Classifier: Intended Audience :: Science/Research
Classifier: License :: OSI Approved :: MIT License
Classifier: Programming Language :: Python :: 3.5
Classifier: Programming Language :: Python :: 3.6
Classifier: Programming Language :: Python :: 3.7
